pyalmanac/__init__.py
pyalmanac/__main__.py
pyalmanac/data/A4chartNorth_P.pdf
pyalmanac/data/A4chartSouth_P.pdf
pyalmanac/data/Ra.jpg
pyalmanac/data/__init__.py
pyalmanac/docs/Explanation.pdf
pyalmanac/docs/__init__.py
pyalmanac/lib/__init__.py
pyalmanac/lib/alma_ephem.py
pyalmanac/lib/config.py
pyalmanac/lib/eventtables.py
pyalmanac/lib/increments.py
pyalmanac/lib/nautical.py
pyalmanac/lib/suntables.py
pyalmanac-1.4.4.dist-info/LICENSE
pyalmanac-1.4.4.dist-info/METADATA
pyalmanac-1.4.4.dist-info/WHEEL
pyalmanac-1.4.4.dist-info/top_level.txt
pyalmanac-1.4.4.dist-info/RECORD
