Metadata-Version: 2.1
Name: pyalmanac
Version: 1.4.4
Summary: Creates the daily pages of a Nautical Almanac using Ephem
Home-page: https://github.com/aendie/Pyalmanac-Py3
Author: Andrew Bauer
Author-email: aendie.bauer@gmail.com
License: GPL-2.0 License
Classifier: Natural Language :: English
Classifier: Operating System :: OS Independent
Classifier: Development Status :: 5 - Production/Stable
Classifier: License :: OSI Approved :: GNU General Public License v2 (GPLv2)
Classifier: Programming Language :: Python :: 3
Classifier: Programming Language :: Python :: 3.4
Classifier: Programming Language :: Python :: 3.5
Classifier: Programming Language :: Python :: 3.6
Classifier: Programming Language :: Python :: 3.7
Classifier: Programming Language :: Python :: 3.8
Classifier: Programming Language :: Python :: 3.9
Classifier: Programming Language :: Python :: 3.10
Classifier: Topic :: Scientific/Engineering :: Astronomy
Requires-Python: >=3.4
License-File: LICENSE
Requires-Dist: Ephem (==4.1)
